setup.py
pairing/__init__.py
pairing/main.py
pairing.egg-info/PKG-INFO
pairing.egg-info/SOURCES.txt
pairing.egg-info/dependency_links.txt
pairing.egg-info/pbr.json
pairing.egg-info/top_level.txt