Metadata-Version: 1.1
Name: pairing
Version: 0.1.3
Summary: Encode pairs of integers as single integer values using the Cantor pairing algorithm
Home-page: https://github.com/perrygeo/pairing
Author: Matthew Perry
Author-email: perrygeo@gmail.com
License: BSD
Keywords: encoding pairing cantor
Platform: UNKNOWN
Classifier: Development Status :: 1 - Planning
Classifier: Topic :: Utilities
Classifier: License :: OSI Approved :: BSD License
Classifier: Intended Audience :: Developers
Classifier: Intended Audience :: Science/Research
Classifier: Operating System :: OS Independent
Classifier: Programming Language :: Python
